{
    "ca": {
        "classic": {}, 
        "collection-title": {}, 
        "container-phrase": {}, 
        "container-title": {
            "Federal Court Reports": "F.C.", 
            "Ontario Reports Second": "!jurisdiction>>>O.R. (2d)", 
            "Supreme Court Reports": "!authority>>>S.C.R."
        }, 
        "hereinafter": {}, 
        "institution-entire": {
            "Supreme Court": "!authority>>>SCC"
        }, 
        "institution-part": {
            "Court of Appeal": "C.A.", 
            "Supreme Court": "S.C."
        }, 
        "nickname": {}, 
        "number": {}, 
        "place": {}, 
        "title": {}, 
        "title-phrase": {}
    }, 
    "ca;on": {
        "classic": {}, 
        "collection-title": {}, 
        "container-phrase": {}, 
        "container-title": {}, 
        "hereinafter": {}, 
        "institution-entire": {}, 
        "institution-part": {
            "High Court of Justice": "H Ct J"
        }, 
        "nickname": {}, 
        "number": {}, 
        "place": {}, 
        "title": {}, 
        "title-phrase": {}
    }, 
    "coe.int": {
        "classic": {}, 
        "collection-title": {}, 
        "container-phrase": {}, 
        "container-title": {
            "Collection of Decisions": "Eur. Comm'n H.R. Col. Dec.", 
            "Decisions and Reports": "Eur. Comm'n H.R. Dec. & Rep.", 
            "Reports of Judgments and Decisions (Series A)": "Eur. Ct. H.R. (ser. A)"
        }, 
        "hereinafter": {}, 
        "institution-entire": {
            "European Court of Human Rights": "Eur. Ct. H.R."
        }, 
        "institution-part": {
            "European Commission of Human Rights": "Eur. Comm'n H.R.", 
            "European Court of Human Rights": "Eur. Ct. H.R."
        }, 
        "nickname": {}, 
        "number": {}, 
        "place": {}, 
        "title": {}, 
        "title-phrase": {}
    }, 
    "default": {
        "classic": {}, 
        "collection-title": {}, 
        "container-phrase": {}, 
        "container-title": {
            "All England Reports": "All E.R.", 
            "Butterworths Medico-Legal Reports": "B.M.L.R.", 
            "European Human Rights Reports": "E.H.R.R."
        }, 
        "hereinafter": {}, 
        "institution-entire": {}, 
        "institution-part": {
            "Columbia Broadcasting System": "CBS", 
            "Publishing House LLC": "Publishing House"
        }, 
        "nickname": {
            "Frank Bennett": "the author"
        }, 
        "number": {
            "Online Edition": "Online edition"
        }, 
        "place": {
            "au.int": "A.U.", 
            "ca": "Can.", 
            "ca;ab": "Alta.", 
            "ca;bc": "B.C.", 
            "ca;federal": "Can.", 
            "ca;federal;ab": "Alta.", 
            "ca;federal;bc": "B.C.", 
            "ca;federal;mb": "Man.", 
            "ca;federal;nb": "N.B.", 
            "ca;federal;nl": "Nfld.", 
            "ca;federal;ns": "N.S.", 
            "ca;federal;nt": "N.W.T.", 
            "ca;federal;nu": "Nun.", 
            "ca;federal;on": "Ont.", 
            "ca;federal;pe": "P.E.I.", 
            "ca;federal;qc": "Que.", 
            "ca;federal;sk": "Sask.", 
            "ca;federal;yt": "Yukon", 
            "ca;mb": "Man.", 
            "ca;nb": "N.B.", 
            "ca;nl": "Nfld.", 
            "ca;ns": "N.S.", 
            "ca;nt": "N.W.T.", 
            "ca;nu": "Nun.", 
            "ca;on": "Ont.", 
            "ca;pe": "P.E.I.", 
            "ca;qc": "Que.", 
            "ca;sk": "Sask.", 
            "ca;yt": "Yukon", 
            "jp": "Japan", 
            "kh": "Kh.", 
            "nz": "N.Z.", 
            "us": "U.S.", 
            "us;ak": "Alaska", 
            "us;al": "Ala.", 
            "us;ar": "Ark.", 
            "us;az": "Ariz.", 
            "us;ca": "Cal.", 
            "us;co": "Colo.", 
            "us;ct": "Conn.", 
            "us;de": "Del.", 
            "us;federal;1-cir": "1st Cir.",
            "us;federal;1-cir-bankr": "B.A.P. 1st Cir.",
            "us;federal;2-cir": "2d Cir.",
            "us;federal;2-cir-bankr": "B.A.P. 2d Cir.",
            "us;federal;3-cir": "3d Cir.",
            "us;federal;3-cir-bankr": "B.A.P. 3d Cir.",
            "us;federal;4-cir": "4th Cir.",
            "us;federal;4-cir-bankr": "B.A.P. 4th Cir.",
            "us;federal;5-cir": "5th Cir.",
            "us;federal;5-cir-bankr": "B.A.P. 5th Cir.",
            "us;federal;6-cir": "6th Cir.",
            "us;federal;6-cir-bankr": "B.A.P. 6th Cir.",
            "us;federal;7-cir": "7th Cir.",
            "us;federal;7-cir-bankr": "B.A.P. 7th Cir.",
            "us;federal;8-cir": "8th Cir.",
            "us;federal;8-cir-bankr": "B.A.P. 8th Cir.",
            "us;federal;9-cir": "9th Cir.",
            "us;federal;9-cir-bankr": "B.A.P. 9th Cir.",
            "us;federal;10-cir": "10th Cir.",
            "us;federal;10-cir-bankr": "B.A.P. 10th Cir.",
            "us;federal;11-cir": "11th Cir.",
            "us;federal;11-cir-bankr": "B.A.P. 11th Cir.",
            "us;federal;ak": "D. Alaska", 
            "us;federal;ak-bankr": "Bankr. D. Alaska", 
            "us;federal;al.middle": "M.D. Ala.", 
            "us;federal;al.middle-bankr": "Bankr. M.D. Ala.", 
            "us;federal;al.northern": "N.D. Ala.", 
            "us;federal;al.northern-bankr": "Bankr. N.D. Ala.", 
            "us;federal;al.southern": "S.D. Ala.", 
            "us;federal;al.southern-bankr": "Bankr. S.D. Ala.", 
            "us;federal;ar.eastern": "E.D. Ark.", 
            "us;federal;ar.eastern-bankr": "Bankr. E.D. Ark.", 
            "us;federal;ar.western": "W.D. Ark.", 
            "us;federal;ar.western-bankr": "Bankr. W.D. Ark.", 
            "us;federal;az": "D. Ariz.", 
            "us;federal;az-bankr": "Bankr. D. Ariz.", 
            "us;federal;ca.central": "C.D. Cal.", 
            "us;federal;ca.central-bankr": "Bankr. C.D. Cal.", 
            "us;federal;ca.eastern": "E.D. Cal.", 
            "us;federal;ca.eastern-bankr": "Bankr. E.D. Cal.", 
            "us;federal;ca.northern": "N.D. Cal.", 
            "us;federal;ca.northern-bankr": "Bankr. N.D. Cal.", 
            "us;federal;ca.southern": "S.D. Cal.", 
            "us;federal;ca.southern-bankr": "Bankr. S.D. Cal.", 
            "us;federal;co": "D. Colo.", 
            "us;federal;co-bankr": "Bankr. D. Colo.", 
            "us;federal;ct": "D. Conn.", 
            "us;federal;ct-bankr": "Bankr. D. Conn.", 
            "us;federal;dc": "D.D.C.", 
            "us;federal;dc-bankr": "Bankr. D.D.C.", 
            "us;federal;de": "D. Del.", 
            "us;federal;de-bankr": "Bankr. D. Del.", 
            "us;federal;fl.middle": "M.D. Fla.", 
            "us;federal;fl.middle-bankr": "Bankr. M.D. Fla.", 
            "us;federal;fl.northern": "N.D. Fla.", 
            "us;federal;fl.northern-bankr": "Bankr. N.D. Fla.", 
            "us;federal;fl.southern": "S.D. Fla.", 
            "us;federal;fl.southern-bankr": "Bankr. S.D. Fla.", 
            "us;federal;ga.middle": "M.D. Ga.", 
            "us;federal;ga.middle-bankr": "Bankr. M.D. Ga.", 
            "us;federal;ga.northern": "N.D. Ga.", 
            "us;federal;ga.northern-bankr": "Bankr. N.D. Ga.", 
            "us;federal;ga.southern": "S.D. Ga.", 
            "us;federal;ga.southern-bankr": "Bankr. S.D. Ga.", 
            "us;federal;hi": "D. Haw.", 
            "us;federal;hi-bankr": "Bankr. D. Haw.", 
            "us;federal;ia.northern": "N.D. Iowa", 
            "us;federal;ia.northern-bankr": "Bankr. N.D. Iowa", 
            "us;federal;ia.southern": "S.D. Iowa", 
            "us;federal;ia.southern-bankr": "Bankr. S.D. Iowa", 
            "us;federal;id": "D. Idaho", 
            "us;federal;id-bankr": "Bankr. D. Idaho", 
            "us;federal;il.central": "C.D. Ill.", 
            "us;federal;il.central-bankr": "Bankr. C.D. Ill.", 
            "us;federal;il.northern": "N.D. Ill.", 
            "us;federal;il.northern-bankr": "Bankr. N.D. Ill.", 
            "us;federal;il.southern": "S.D. Ill.", 
            "us;federal;il.southern-bankr": "Bankr. S.D. Ill.", 
            "us;federal;in.northern": "N.D. Ind.", 
            "us;federal;in.northern-bankr": "Bankr. N.D. Ind.", 
            "us;federal;in.southern": "S.D. Ind.", 
            "us;federal;in.southern-bankr": "Bankr. S.D. Ind.", 
            "us;federal;ks": "D. Kan.", 
            "us;federal;ks-bankr": "Bankr. D. Kan.", 
            "us;federal;ky.eastern": "E.D. Ky.", 
            "us;federal;ky.eastern-bankr": "Bankr. E.D. Ky.", 
            "us;federal;ky.western": "W.D. Ky.", 
            "us;federal;ky.western-bankr": "Bankr. W.D. Ky.", 
            "us;federal;la.eastern": "E.D. La.", 
            "us;federal;la.eastern-bankr": "Bankr. E.D. La.", 
            "us;federal;la.middle": "M.D. La.", 
            "us;federal;la.middle-bankr": "Bankr. M.D. La.", 
            "us;federal;la.western": "W.D. La.", 
            "us;federal;la.western-bankr": "Bankr. W.D. La.", 
            "us;federal;ma": "D. Mass.", 
            "us;federal;ma-bankr": "Bankr. D. Mass.", 
            "us;federal;md": "D. Md.", 
            "us;federal;md-bankr": "Bankr. D. Md.", 
            "us;federal;me": "D. Me.", 
            "us;federal;me-bankr": "Bankr. D. Me.", 
            "us;federal;mi.eastern": "E.D. Mich.", 
            "us;federal;mi.eastern-bankr": "Bankr. E.D. Mich.", 
            "us;federal;mi.western": "W.D. Mich.", 
            "us;federal;mi.western-bankr": "Bankr. W.D. Mich.", 
            "us;federal;mn": "D. Minn.", 
            "us;federal;mn-bankr": "Bankr. D. Minn.", 
            "us;federal;mo.eastern": "E.D. Mo.", 
            "us;federal;mo.eastern-bankr": "Bankr. E.D. Mo.", 
            "us;federal;mo.western": "W.D. Mo.", 
            "us;federal;mo.western-bankr": "Bankr. W.D. Mo.", 
            "us;federal;ms.northern": "N.D. Miss.", 
            "us;federal;ms.northern-bankr": "Bankr. N.D. Miss.", 
            "us;federal;ms.southern": "S.D. Miss.", 
            "us;federal;ms.southern-bankr": "Bankr. S.D. Miss.", 
            "us;federal;mt": "D. Mont.", 
            "us;federal;mt-bankr": "Bankr. D. Mont.", 
            "us;federal;nc.eastern": "E.D.N.C.", 
            "us;federal;nc.eastern-bankr": "Bankr. E.D.N.C.", 
            "us;federal;nc.middle": "M.D.N.C.", 
            "us;federal;nc.middle-bankr": "Bankr. M.D.N.C.", 
            "us;federal;nc.western": "W.D.N.C.", 
            "us;federal;nc.western-bankr": "Bankr. W.D.N.C.", 
            "us;federal-bankr;nd": "D.N.D.", 
            "us;federal-bankr;nd-bankr": "Bankr. D.N.D.", 
            "us;federal;ne": "D. Neb.", 
            "us;federal;ne-bankr": "Bankr. D. Neb.", 
            "us;federal;nh": "D.N.H.", 
            "us;federal;nh-bankr": "Bankr. D.N.H.", 
            "us;federal;nj": "D.N.J.", 
            "us;federal;nj-bankr": "Bankr. D.N.J.", 
            "us;federal;nm": "D.N.M.", 
            "us;federal;nm-bankr": "Bankr. D.N.M.", 
            "us;federal;nv": "D. Nev.", 
            "us;federal;nv-bankr": "Bankr. D. Nev.", 
            "us;federal;ny.eastern": "E.D.N.Y.", 
            "us;federal;ny.eastern-bankr": "Bankr. E.D.N.Y.", 
            "us;federal;ny.northern": "N.D.N.Y.", 
            "us;federal;ny.northern-bankr": "Bankr. N.D.N.Y.", 
            "us;federal;ny.southern": "S.D.N.Y.", 
            "us;federal;ny.southern-bankr": "Bankr. S.D.N.Y.", 
            "us;federal;ny.western": "W.D.N.Y.", 
            "us;federal;ny.western-bankr": "Bankr. W.D.N.Y.", 
            "us;federal;oh.northern": "N.D. Ohio", 
            "us;federal;oh.northern-bankr": "Bankr. N.D. Ohio", 
            "us;federal;oh.southern": "S.D. Ohio", 
            "us;federal;oh.southern-bankr": "Bankr. S.D. Ohio", 
            "us;federal;ok.eastern": "E.D. Okla.", 
            "us;federal;ok.eastern-bankr": "Bankr. E.D. Okla.", 
            "us;federal;ok.northern": "N.D. Okla.", 
            "us;federal;ok.northern-bankr": "Bankr. N.D. Okla.", 
            "us;federal;ok.western": "W.D. Okla.", 
            "us;federal;ok.western-bankr": "Bankr. W.D. Okla.", 
            "us;federal;or": "D. Or.", 
            "us;federal;or-bankr": "Bankr. D. Or.", 
            "us;federal;pa.eastern": "E.D. Pa.", 
            "us;federal;pa.eastern-bankr": "Bankr. E.D. Pa.", 
            "us;federal;pa.middle": "M.D. Pa.", 
            "us;federal;pa.middle-bankr": "Bankr. M.D. Pa.", 
            "us;federal;pa.western": "W.D. Pa.", 
            "us;federal;pa.western-bankr": "Bankr. W.D. Pa.", 
            "us;federal;pr": "D. Puerto Rico", 
            "us;federal;pr-bankr": "Bankr. D. Puerto Rico", 
            "us;federal;ri": "D.R.I.", 
            "us;federal;ri-bankr": "Bankr. D.R.I.", 
            "us;federal;sc": "D.S.C.", 
            "us;federal;sc-bankr": "Bankr. D.S.C.", 
            "us;federal-bankr;sd": "D.S.D.", 
            "us;federal-bankr;sd-bankr": "Bankr. D.S.D.", 
            "us;federal;tn.eastern": "E.D. Tenn.", 
            "us;federal;tn.eastern-bankr": "Bankr. E.D. Tenn.", 
            "us;federal;tn.middle": "M.D. Tenn.", 
            "us;federal;tn.middle-bankr": "Bankr. M.D. Tenn.", 
            "us;federal;tn.western": "W.D. Tenn.", 
            "us;federal;tn.western-bankr": "Bankr. W.D. Tenn.", 
            "us;federal;tx.eastern": "E.D. Tex.", 
            "us;federal;tx.eastern-bankr": "Bankr. E.D. Tex.", 
            "us;federal;tx.northern": "N.D. Tex.", 
            "us;federal;tx.northern-bankr": "Bankr. N.D. Tex.", 
            "us;federal;tx.southern": "S.D. Tex.", 
            "us;federal;tx.southern-bankr": "Bankr. S.D. Tex.", 
            "us;federal;tx.western": "W.D. Tex.", 
            "us;federal;tx.western-bankr": "Bankr. W.D. Tex.", 
            "us;federal;ut": "D. Utah", 
            "us;federal;ut-bankr": "Bankr. D. Utah", 
            "us;federal;va.eastern": "E.D. Va.", 
            "us;federal;va.eastern-bankr": "Bankr. E.D. Va.", 
            "us;federal;va.western": "W.D. Va.", 
            "us;federal;va.western-bankr": "Bankr. W.D. Va.", 
            "us;federal-bankr;vt": " D. Vt.", 
            "us;federal-bankr;vt-bankr": "Bankr. D. Vt.", 
            "us;federal;wa.eastern": "E.D. Wash.", 
            "us;federal;wa.eastern-bankr": "Bankr. E.D. Wash.", 
            "us;federal;wa.western": "W.D. Wash.", 
            "us;federal;wa.western-bankr": "Bankr. W.D. Wash.", 
            "us;federal;wi.eastern": "E.D. Wis.", 
            "us;federal;wi.eastern-bankr": "Bankr. E.D. Wis.", 
            "us;federal;wi.western": "W.D. Wis.", 
            "us;federal;wi.western-bankr": "Bankr. W.D. Wis.", 
            "us;federal;wv.northern": "N.D. W.Va.", 
            "us;federal;wv.northern-bankr": "Bankr. N.D. W.Va.", 
            "us;federal;wv.southern": "S.D. W.Va.", 
            "us;federal;wv.southern-bankr": "Bankr. S.D. W.Va.", 
            "us;federal;wy": "D. Wyo.", 
            "us;federal;wy-bankr": "Bankr. D. Wyo.", 
            "us;fl": "Fla.", 
            "us;ga": "Ga.", 
            "us;hi": "Haw.", 
            "us;ia": "Iowa", 
            "us;id": "Idaho", 
            "us;il": "Ill.", 
            "us;in": "Ind.", 
            "us;ks": "Kan.", 
            "us;ky": "Ky.", 
            "us;la": "La.", 
            "us;ma": "Mass.", 
            "us;md": "Md.", 
            "us;me": "Me.", 
            "us;mi": "Mich.", 
            "us;mn": "Minn.", 
            "us;mo": "Mo.", 
            "us;ms": "Miss.", 
            "us;mt": "Mont.", 
            "us;nc": "N.C.", 
            "us;nd": "N.D.", 
            "us;ne": "Neb.", 
            "us;nh": "N.H.", 
            "us;nj": "N.J.", 
            "us;nm": "N.M.", 
            "us;nv": "Nev.", 
            "us;ny": "N.Y.", 
            "us;oh": "Ohio", 
            "us;ok": "Okla.", 
            "us;or": "Or.", 
            "us;pa": "Pa.", 
            "us;pr": "Puerto Rico", 
            "us;ri": "R.I.", 
            "us;sc": "S.C.", 
            "us;sd": "S.D.", 
            "us;tn": "Tenn.", 
            "us;tx": "Tex.", 
            "us;ut": "Utah", 
            "us;va": "Va.", 
            "us;vt": "Vt.", 
            "us;wa": "Wash.", 
            "us;wi": "Wis.", 
            "us;wv": "W.Va.", 
            "us;wy": "Wyo."
        }, 
        "title": {}, 
        "title-phrase": {}
    }, 
    "gb": {
        "classic": {}, 
        "collection-title": {}, 
        "container-phrase": {}, 
        "container-title": {}, 
        "hereinafter": {}, 
        "institution-entire": {}, 
        "institution-part": {
            "House of Lords": "H.L."
        }, 
        "nickname": {}, 
        "number": {}, 
        "place": {}, 
        "title": {
            "George III": "Geo 3"
        }, 
        "title-phrase": {}
    }, 
    "gb;england.and.wales": {
        "classic": {}, 
        "collection-title": {}, 
        "container-phrase": {}, 
        "container-title": {}, 
        "hereinafter": {}, 
        "institution-entire": {
            "Court of Appeal|Civil Division": "EWCA Civ", 
            "High Court": "EWHC"
        }, 
        "institution-part": {
            "Chancery": "Ch.", 
            "Court of Appeal": "C.A.", 
            "Queen's Bench": "Q.B."
        }, 
        "nickname": {}, 
        "number": {}, 
        "place": {}, 
        "title": {}, 
        "title-phrase": {}
    }, 
    "nz": {
        "classic": {}, 
        "collection-title": {}, 
        "container-phrase": {}, 
        "container-title": {}, 
        "hereinafter": {}, 
        "institution-entire": {}, 
        "institution-part": {
            "High Court": "H.C."
        }, 
        "nickname": {}, 
        "number": {}, 
        "place": {}, 
        "title": {}, 
        "title-phrase": {}
    }, 
    "un.org": {
        "classic": {}, 
        "collection-title": {}, 
        "container-phrase": {}, 
        "container-title": {
            "United Nations General Assembly Official Record": "U.N. GAOR"
        }, 
        "hereinafter": {}, 
        "institution-entire": {}, 
        "institution-part": {
            "General Assembly": "G.A.", 
            "High Court": "H.C."
        }, 
        "nickname": {}, 
        "number": {}, 
        "place": {}, 
        "title": {
            "Resolution": "Res."
        }, 
        "title-phrase": {}
    }, 
    "us": {
        "classic": {}, 
        "collection-title": {}, 
        "container-phrase": {}, 
        "container-title": {
            "A. 2d": "A.2d", 
            "A. 3d": "A.3d", 
            "Atlantic Reporter": "A.", 
            "Atlantic Reporter 2d": "A.2d", 
            "Atlantic Reporter 3d": "A.3d", 
            "B. R.": "B.R.", 
            "BR": "B.R.", 
            "Bankruptcy Reporter": "B.R.", 
            "Court of International Trade Reports": "Ct. Int'l Trade", 
            "Ct.Cl.": "Ct. Cl.", 
            "Ct.Int'l Trade": "Ct. Int'l Trade", 
            "F. 2d": "!jurisdiction>>>F.2d", 
            "F. 3d": "!jurisdiction>>>F.3d", 
            "F. Supp.2d": "F. Supp. 2d", 
            "F.2d": "!jurisdiction>>>F.2d", 
            "F.3d": "!jurisdiction>>>F.3d", 
            "F.Supp.": "F. Supp.", 
            "F.Supp. 2d": "F. Supp. 2d", 
            "F.Supp.2d": "F. Supp. 2d", 
            "Fed.Cl.": "Fed. Cl.", 
            "Federal Claims Reporter": "Fed. Cl.", 
            "Federal Reporter": "F.", 
            "Federal Supplement": "F. Supp.", 
            "Federal Supplement 2d": "F. Supp. 2d", 
            "Kan.App.": "Kan. App.", 
            "Kansas Court of Appeals Reports": "Kan. App.", 
            "L. Ed.2d": "L. Ed. 2d", 
            "L.Ed.": "L. Ed.", 
            "L.Ed. 2d": "L. Ed. 2d", 
            "L.Ed.2d": "L. Ed. 2d", 
            "M. J.": "M.J.", 
            "N. E.": "N.E.", 
            "N. E. 2d": "N.E.2d", 
            "N. E.2d": "N.E.2d", 
            "N. W.": "N.W.", 
            "N. W. 2d": "N.W.2d", 
            "N. W.2d": "N.W.2d", 
            "N.E. 2d": "N.E.2d", 
            "N.W. 2d": "N.W.2d", 
            "NE 2d": "N.E.2d", 
            "NW 2d": "N.W.2d", 
            "North Eastern Reporter": "N.E.", 
            "North Eastern Reporter 2d": "N.E.2d", 
            "North Western Reporter": "N.W.", 
            "Northwest Reporter Second": "N.W.2d", 
            "P. 2d": "P.2d", 
            "P. 3d": "P.3d", 
            "Pacific Reporter": "P.", 
            "Pacific Reporter 2d": "P.2d", 
            "Pacific Reporter 3d": "P.3d", 
            "Pennsylvania Statutes Annotated": "Pa. Stat. Ann.", 
            "S. E.": "S.E.", 
            "S. E. 2d": "S.E.2d", 
            "S. E.2d": "S.E.2d", 
            "S. W.": "S.W.", 
            "S. W. 2d": "S.W.2d", 
            "S. W. 3d": "S.W.3d", 
            "S. W.2d": "S.W.2d", 
            "S. W.3d": "S.W.3d", 
            "S.Ct": "S. Ct.", 
            "S.E. 2d": "S.E.2d", 
            "S.W. 2d": "S.W.2d", 
            "S.W. 3d": "S.W.3d", 
            "SE 2d": "S.E.2d", 
            "SW 3d": "S.W.3d", 
            "So.2d": "So. 2d", 
            "So.3d": "So. 3d", 
            "South Eastern Reporter": "S.E.", 
            "South Eastern Reporter 2d": "S.E.2d", 
            "South Western": "S.W.", 
            "South Western 2d": "S.W.2d", 
            "South Western 3d": "S.W.3d", 
            "Southern Reporter": "So.", 
            "Southern Reporter 2d": "So. 2d", 
            "Southern Reporter 3d": "So. 3d", 
            "Statutes at Large": "Stat.", 
            "Supreme Court": "Wall.", 
            "T. C.": "T.C.", 
            "U. S.": "!jurisdiction,authority>>>U.S.", 
            "US Code": "U.S.C.", 
            "United States Claims Reporter": "Ct. Cl.", 
            "United States Reports": "!jurisdiction,authority>>>U.S.", 
            "United States Tax Court Reports": "T.C.", 
            "Vet.App.": "Vet. App.", 
            "West's Military Justice Reporter": "M.J.", 
            "West's Veterans Appeals Reporter": "Vet. App.", 
            "Wisconsin Reporter Second": "!jurisdiction,authority>>>Wisc.2d"
        }, 
        "hereinafter": {}, 
        "institution-entire": {}, 
        "institution-part": {
            "House of Representatives": "H.R.", 
            "Supreme Court": "Sup. Ct.", 
            "U.S. Congress": "Cong."
        }, 
        "nickname": {}, 
        "number": {}, 
        "place": {}, 
        "title": {
            "House of Representatives Joint Resolution": "H.R.J. Res.", 
            "Senate Joint Resolution": "S.J. Res.", 
            "Special Session": "Spec. Sess."
        }, 
        "title-phrase": {}
    }, 
    "us;ak": {
        "classic": {}, 
        "collection-title": {}, 
        "container-phrase": {}, 
        "container-title": {
            "Alaska Reports": "Alaska"
        }, 
        "hereinafter": {}, 
        "institution-entire": {}, 
        "institution-part": {}, 
        "nickname": {}, 
        "number": {}, 
        "place": {}, 
        "title": {}, 
        "title-phrase": {}
    }, 
    "us;al": {
        "classic": {}, 
        "collection-title": {}, 
        "container-phrase": {}, 
        "container-title": {
            "Alabama Reports": "Ala."
        }, 
        "hereinafter": {}, 
        "institution-entire": {}, 
        "institution-part": {}, 
        "nickname": {}, 
        "number": {}, 
        "place": {}, 
        "title": {}, 
        "title-phrase": {}
    }, 
    "us;ar": {
        "classic": {}, 
        "collection-title": {}, 
        "container-phrase": {}, 
        "container-title": {
            "Arkansas Reports": "Ark."
        }, 
        "hereinafter": {}, 
        "institution-entire": {}, 
        "institution-part": {}, 
        "nickname": {}, 
        "number": {}, 
        "place": {}, 
        "title": {}, 
        "title-phrase": {}
    }, 
    "us;az": {
        "classic": {}, 
        "collection-title": {}, 
        "container-phrase": {}, 
        "container-title": {
            "Arizona Appeals Reports": "Ariz. App.", 
            "Arizona Reports": "Ariz."
        }, 
        "hereinafter": {}, 
        "institution-entire": {}, 
        "institution-part": {}, 
        "nickname": {}, 
        "number": {}, 
        "place": {}, 
        "title": {}, 
        "title-phrase": {}
    }, 
    "us;ca": {
        "classic": {}, 
        "collection-title": {}, 
        "container-phrase": {}, 
        "container-title": {
            "Cal. App.2d": "Cal. App. 2d", 
            "Cal. App.3d": "Cal. App. 3d", 
            "Cal. App.4th": "Cal. App. 4th", 
            "Cal. Rptr.2d": "Cal. Rptr. 2d", 
            "Cal. Rptr.3d": "Cal. Rptr. 3d", 
            "Cal.2d": "Cal. 2d", 
            "Cal.3d": "Cal. 3d", 
            "Cal.4th": "Cal. 4th", 
            "Cal.App.": "Cal. App.", 
            "Cal.App. 2d": "Cal. App. 2d", 
            "Cal.App. 2d Supp.": "Cal. App. Supp. 2d", 
            "Cal.App. 3d": "Cal. App. 3d", 
            "Cal.App. 3d Supp.": "Cal. App. Supp. 3d", 
            "Cal.App. 4th": "Cal. App. 4th", 
            "Cal.App. Supp. 2d": "Cal. App. Supp. 2d", 
            "Cal.App. Supp. 3d": "Cal. App. Supp. 3d", 
            "Cal.App. Supp.2d": "Cal. App. Supp. 2d", 
            "Cal.App. Supp.3d": "Cal. App. Supp. 3d", 
            "Cal.App.2d": "Cal. App. 2d", 
            "Cal.App.2d Supp.": "Cal. App. Supp. 2d", 
            "Cal.App.3d": "Cal. App. 3d", 
            "Cal.App.3d Supp.": "Cal. App. Supp. 3d", 
            "Cal.App.4th": "Cal. App. 4th", 
            "Cal.App.Supp.": "Cal. App. Supp.", 
            "Cal.Rptr.": "Cal. Rptr.", 
            "Cal.Rptr. 2d": "Cal. Rptr. 2d", 
            "Cal.Rptr. 3d": "Cal. Rptr. 3d", 
            "Cal.Rptr.2d": "Cal. Rptr. 2d", 
            "Cal.Rptr.3d": "Cal. Rptr. 3d", 
            "California Appellate Reports": "Cal. App.", 
            "California Appellate Reports 2d": "Cal. App. 2d", 
            "California Appellate Reports 3d": "Cal. App. 3d", 
            "California Appellate Reports 4th": "Cal. App. 4th", 
            "California Appellate Reports Supplement": "Cal. App. Supp.", 
            "California Appellate Reports Supplement 2d": "Cal. App. Supp. 2d", 
            "California Appellate Reports Supplement 3d": "Cal. App. Supp. 3d", 
            "California Reports": "Cal.", 
            "California Reports 2d": "Cal. 2d", 
            "California Reports 3d": "Cal. 3d", 
            "California Reports 4th": "Cal. 4th", 
            "West\u2019s California Reporter": "Cal. Rptr.", 
            "West\u2019s California Reporter 2d": "Cal. Rptr. 2d", 
            "West\u2019s California Reporter 3d": "Cal. Rptr. 3d"
        }, 
        "hereinafter": {}, 
        "institution-entire": {}, 
        "institution-part": {}, 
        "nickname": {}, 
        "number": {}, 
        "place": {}, 
        "title": {}, 
        "title-phrase": {}
    }, 
    "us;co": {
        "classic": {}, 
        "collection-title": {}, 
        "container-phrase": {}, 
        "container-title": {
            "Colorado Reports": "Colo."
        }, 
        "hereinafter": {}, 
        "institution-entire": {}, 
        "institution-part": {}, 
        "nickname": {}, 
        "number": {}, 
        "place": {}, 
        "title": {}, 
        "title-phrase": {}
    }, 
    "us;ct": {
        "classic": {}, 
        "collection-title": {}, 
        "container-phrase": {}, 
        "container-title": {
            "Connecticut Appellate Reports": "Conn. App.", 
            "Connecticut Reports": "Conn."
        }, 
        "hereinafter": {}, 
        "institution-entire": {}, 
        "institution-part": {}, 
        "nickname": {}, 
        "number": {}, 
        "place": {}, 
        "title": {}, 
        "title-phrase": {}
    }, 
    "us;de": {
        "classic": {}, 
        "collection-title": {}, 
        "container-phrase": {}, 
        "container-title": {
            "Delaware Reports": "Del."
        }, 
        "hereinafter": {}, 
        "institution-entire": {}, 
        "institution-part": {}, 
        "nickname": {}, 
        "number": {}, 
        "place": {}, 
        "title": {}, 
        "title-phrase": {}
    }, 
    "us;federal": {
        "classic": {}, 
        "collection-title": {}, 
        "container-phrase": {}, 
        "container-title": {}, 
        "hereinafter": {}, 
        "institution-entire": {}, 
        "institution-part": {
            "Bankruptcy Court": "Bankr.", 
            "District Court": "!here>>>", 
            "Eighth Circuit Court of Appeals": "8th Cir.", 
            "Eleventh Circuit Court of Appeals": "11th Cir.", 
            "Fifth Circuit Court of Appeals": "5th Cir.", 
            "First Circuit Court of Appeals": "1st Cir.", 
            "Fourth Circuit Court of Appeals": "4th Cir.", 
            "Ninth Circuit Court of Appeals": "9th Cir.", 
            "Second Circuit Court of Appeals": "2nd Cir.", 
            "Seventh Circuit Court of Appeals": "7th Cir.", 
            "Sixth Circuit Court of Appeals": "6th Cir.", 
            "Tenth Circuit Court of Appeals": "10th Cir.", 
            "Third Circuit Court of Appeals": "3rd Cir."
        }, 
        "nickname": {}, 
        "number": {}, 
        "place": {}, 
        "title": {}, 
        "title-phrase": {}
    }, 
    "us;federal;dc": {
        "classic": {}, 
        "collection-title": {}, 
        "container-phrase": {}, 
        "container-title": {
            "District of Columbia Reports": "D.C."
        }, 
        "hereinafter": {}, 
        "institution-entire": {}, 
        "institution-part": {}, 
        "nickname": {}, 
        "number": {}, 
        "place": {}, 
        "title": {}, 
        "title-phrase": {}
    }, 
    "us;fl": {
        "classic": {}, 
        "collection-title": {}, 
        "container-phrase": {}, 
        "container-title": {
            "Florida Reports": "Fla."
        }, 
        "hereinafter": {}, 
        "institution-entire": {}, 
        "institution-part": {}, 
        "nickname": {}, 
        "number": {}, 
        "place": {}, 
        "title": {}, 
        "title-phrase": {}
    }, 
    "us;ga": {
        "classic": {}, 
        "collection-title": {}, 
        "container-phrase": {}, 
        "container-title": {
            "Georgia Appeals Reports": "Ga. App.", 
            "Georgia Reports": "Ga."
        }, 
        "hereinafter": {}, 
        "institution-entire": {}, 
        "institution-part": {}, 
        "nickname": {}, 
        "number": {}, 
        "place": {}, 
        "title": {}, 
        "title-phrase": {}
    }, 
    "us;hi": {
        "classic": {}, 
        "collection-title": {}, 
        "container-phrase": {}, 
        "container-title": {
            "West\u2019s Hawaii Reports": "Haw."
        }, 
        "hereinafter": {}, 
        "institution-entire": {}, 
        "institution-part": {}, 
        "nickname": {}, 
        "number": {}, 
        "place": {}, 
        "title": {}, 
        "title-phrase": {}
    }, 
    "us;ia": {
        "classic": {}, 
        "collection-title": {}, 
        "container-phrase": {}, 
        "container-title": {
            "Iowa Reports": "Iowa"
        }, 
        "hereinafter": {}, 
        "institution-entire": {}, 
        "institution-part": {}, 
        "nickname": {}, 
        "number": {}, 
        "place": {}, 
        "title": {}, 
        "title-phrase": {}
    }, 
    "us;id": {
        "classic": {}, 
        "collection-title": {}, 
        "container-phrase": {}, 
        "container-title": {
            "Idaho Reports": "Idaho"
        }, 
        "hereinafter": {}, 
        "institution-entire": {}, 
        "institution-part": {}, 
        "nickname": {}, 
        "number": {}, 
        "place": {}, 
        "title": {}, 
        "title-phrase": {}
    }, 
    "us;il": {
        "classic": {}, 
        "collection-title": {}, 
        "container-phrase": {}, 
        "container-title": {
            "Ill. App.2d": "Ill. App. 2d", 
            "Ill. App.3d": "Ill. App. 3d", 
            "Ill.Dec.": "Ill. Dec.", 
            "West\u2019s Illinois Decisions": "Ill. Dec.", 
            "lllinois Appellate Court Reports": "Ill. App.", 
            "lllinois Appellate Court Reports 2d": "Ill. App. 2d", 
            "lllinois Appellate Court Reports 3d": "Ill. App. 3d", 
            "lllinois Reports": "Ill."
        }, 
        "hereinafter": {}, 
        "institution-entire": {}, 
        "institution-part": {}, 
        "nickname": {}, 
        "number": {}, 
        "place": {}, 
        "title": {}, 
        "title-phrase": {}
    }, 
    "us;in": {
        "classic": {}, 
        "collection-title": {}, 
        "container-phrase": {}, 
        "container-title": {
            "Indiana Reports": "Ind."
        }, 
        "hereinafter": {}, 
        "institution-entire": {}, 
        "institution-part": {}, 
        "nickname": {}, 
        "number": {}, 
        "place": {}, 
        "title": {}, 
        "title-phrase": {}
    }, 
    "us;ks": {
        "classic": {}, 
        "collection-title": {}, 
        "container-phrase": {}, 
        "container-title": {
            "Kan. App.2d": "Kan. App. 2d", 
            "Kan.App. 2d": "Kan. App. 2d", 
            "Kan.App.2d": "Kan. App. 2d", 
            "Kansas Court of Appeals Reports 2d": "Kan. App. 2d", 
            "Kansas Reports": "Kan."
        }, 
        "hereinafter": {}, 
        "institution-entire": {}, 
        "institution-part": {}, 
        "nickname": {}, 
        "number": {}, 
        "place": {}, 
        "title": {}, 
        "title-phrase": {}
    }, 
    "us;ky": {
        "classic": {}, 
        "collection-title": {}, 
        "container-phrase": {}, 
        "container-title": {
            "Kentucky Reports": "Ky."
        }, 
        "hereinafter": {}, 
        "institution-entire": {}, 
        "institution-part": {}, 
        "nickname": {}, 
        "number": {}, 
        "place": {}, 
        "title": {}, 
        "title-phrase": {}
    }, 
    "us;la": {
        "classic": {}, 
        "collection-title": {}, 
        "container-phrase": {}, 
        "container-title": {
            "Louisiana Reports": "La."
        }, 
        "hereinafter": {}, 
        "institution-entire": {}, 
        "institution-part": {}, 
        "nickname": {}, 
        "number": {}, 
        "place": {}, 
        "title": {}, 
        "title-phrase": {}
    }, 
    "us;ma": {
        "classic": {}, 
        "collection-title": {}, 
        "container-phrase": {}, 
        "container-title": {
            "Massachusetts Appeals Court Reports": "Mass. App. Ct.", 
            "Massachusetts Reports": "Mass."
        }, 
        "hereinafter": {}, 
        "institution-entire": {}, 
        "institution-part": {}, 
        "nickname": {}, 
        "number": {}, 
        "place": {}, 
        "title": {}, 
        "title-phrase": {}
    }, 
    "us;md": {
        "classic": {}, 
        "collection-title": {}, 
        "container-phrase": {}, 
        "container-title": {
            "Maryland Appellate Reports": "Md. App.", 
            "Maryland Reports": "Md."
        }, 
        "hereinafter": {}, 
        "institution-entire": {}, 
        "institution-part": {}, 
        "nickname": {}, 
        "number": {}, 
        "place": {}, 
        "title": {}, 
        "title-phrase": {}
    }, 
    "us;me": {
        "classic": {}, 
        "collection-title": {}, 
        "container-phrase": {}, 
        "container-title": {
            "Maine Reports": "Me."
        }, 
        "hereinafter": {}, 
        "institution-entire": {}, 
        "institution-part": {}, 
        "nickname": {}, 
        "number": {}, 
        "place": {}, 
        "title": {}, 
        "title-phrase": {}
    }, 
    "us;mi": {
        "classic": {}, 
        "collection-title": {}, 
        "container-phrase": {}, 
        "container-title": {
            "Michigan Appeals Reports": "Mich. App.", 
            "Michigan Reports": "Mich."
        }, 
        "hereinafter": {}, 
        "institution-entire": {}, 
        "institution-part": {}, 
        "nickname": {}, 
        "number": {}, 
        "place": {}, 
        "title": {}, 
        "title-phrase": {}
    }, 
    "us;mn": {
        "classic": {}, 
        "collection-title": {}, 
        "container-phrase": {}, 
        "container-title": {
            "Minnesota Reports": "Minn."
        }, 
        "hereinafter": {}, 
        "institution-entire": {}, 
        "institution-part": {}, 
        "nickname": {}, 
        "number": {}, 
        "place": {}, 
        "title": {}, 
        "title-phrase": {}
    }, 
    "us;mo": {
        "classic": {}, 
        "collection-title": {}, 
        "container-phrase": {}, 
        "container-title": {
            "Missouri Reports": "Mo."
        }, 
        "hereinafter": {}, 
        "institution-entire": {}, 
        "institution-part": {}, 
        "nickname": {}, 
        "number": {}, 
        "place": {}, 
        "title": {}, 
        "title-phrase": {}
    }, 
    "us;ms": {
        "classic": {}, 
        "collection-title": {}, 
        "container-phrase": {}, 
        "container-title": {
            "Mississippi Reports": "Miss."
        }, 
        "hereinafter": {}, 
        "institution-entire": {}, 
        "institution-part": {}, 
        "nickname": {}, 
        "number": {}, 
        "place": {}, 
        "title": {}, 
        "title-phrase": {}
    }, 
    "us;mt": {
        "classic": {}, 
        "collection-title": {}, 
        "container-phrase": {}, 
        "container-title": {
            "Montana Reports": "Mont."
        }, 
        "hereinafter": {}, 
        "institution-entire": {}, 
        "institution-part": {}, 
        "nickname": {}, 
        "number": {}, 
        "place": {}, 
        "title": {}, 
        "title-phrase": {}
    }, 
    "us;nc": {
        "classic": {}, 
        "collection-title": {}, 
        "container-phrase": {}, 
        "container-title": {
            "North Carolina Court of Appeals Reports": "N.C. App.", 
            "North Carolina Reports": "N.C."
        }, 
        "hereinafter": {}, 
        "institution-entire": {}, 
        "institution-part": {}, 
        "nickname": {}, 
        "number": {}, 
        "place": {}, 
        "title": {}, 
        "title-phrase": {}
    }, 
    "us;nd": {
        "classic": {}, 
        "collection-title": {}, 
        "container-phrase": {}, 
        "container-title": {
            "North Dakota Reports": "N.D."
        }, 
        "hereinafter": {}, 
        "institution-entire": {
            "Court of Appeals": "ND App", 
            "Supreme Court": "ND"
        }, 
        "institution-part": {}, 
        "nickname": {}, 
        "number": {}, 
        "place": {}, 
        "title": {}, 
        "title-phrase": {}
    }, 
    "us;ne": {
        "classic": {}, 
        "collection-title": {}, 
        "container-phrase": {}, 
        "container-title": {
            "Nebraska Court of Appeals Reports": "Neb. App.", 
            "Nebraska Reports": "Neb."
        }, 
        "hereinafter": {}, 
        "institution-entire": {}, 
        "institution-part": {}, 
        "nickname": {}, 
        "number": {}, 
        "place": {}, 
        "title": {}, 
        "title-phrase": {}
    }, 
    "us;nh": {
        "classic": {}, 
        "collection-title": {}, 
        "container-phrase": {}, 
        "container-title": {
            "New Hampshire Reports": "N.H."
        }, 
        "hereinafter": {}, 
        "institution-entire": {}, 
        "institution-part": {}, 
        "nickname": {}, 
        "number": {}, 
        "place": {}, 
        "title": {}, 
        "title-phrase": {}
    }, 
    "us;nj": {
        "classic": {}, 
        "collection-title": {}, 
        "container-phrase": {}, 
        "container-title": {
            "New Jersey Reports": "N.J.", 
            "New Jersey Superior Court Reports": "N.J. Super.", 
            "New Jersey Tax Court Reports": "N.J. Tax"
        }, 
        "hereinafter": {}, 
        "institution-entire": {}, 
        "institution-part": {}, 
        "nickname": {}, 
        "number": {}, 
        "place": {}, 
        "title": {}, 
        "title-phrase": {}
    }, 
    "us;nm": {
        "classic": {}, 
        "collection-title": {}, 
        "container-phrase": {}, 
        "container-title": {
            "New Mexico Reports": "N.M."
        }, 
        "hereinafter": {}, 
        "institution-entire": {}, 
        "institution-part": {}, 
        "nickname": {}, 
        "number": {}, 
        "place": {}, 
        "title": {}, 
        "title-phrase": {}
    }, 
    "us;nv": {
        "classic": {}, 
        "collection-title": {}, 
        "container-phrase": {}, 
        "container-title": {
            "Nevada Report": "Nev."
        }, 
        "hereinafter": {}, 
        "institution-entire": {}, 
        "institution-part": {}, 
        "nickname": {}, 
        "number": {}, 
        "place": {}, 
        "title": {}, 
        "title-phrase": {}
    }, 
    "us;ny": {
        "classic": {}, 
        "collection-title": {}, 
        "container-phrase": {}, 
        "container-title": {
            "A.D. 2d": "A.D.2d", 
            "A.D. 3d": "A.D.3d", 
            "AD 2d": "A.D.2d", 
            "AD 3d": "A.D.3d", 
            "Appellate Division Reports 2d": "A.D.", 
            "Appellate Division Reports 3d": "A.D.3d", 
            "Misc 2d": "Misc. 2d", 
            "Misc 3d": "Misc. 3d", 
            "Misc.2d": "Misc. 2d", 
            "Misc.3d": "Misc. 3d", 
            "N. Y.": "N.Y.", 
            "N.Y. 2d": "N.Y.2d", 
            "N.Y. 3d": "N.Y.3d", 
            "N.Y.S. 2d": "N.Y.S.2d", 
            "N.Y.S. 3d": "N.Y.S.3d", 
            "NY 2d": "N.Y.2d", 
            "NY 3d": "N.Y.3d", 
            "NYS 2d": "N.Y.S.2d", 
            "NYS 3d": "N.Y.S.3d", 
            "New York Miscellaneous Reports": "Misc.", 
            "New York Miscellaneous Reports 2d": "Misc. 2d", 
            "New York Miscellaneous Reports 3d": "Misc. 3d", 
            "New York Reports": "N.Y.", 
            "New York Reports 2d": "N.Y.2d", 
            "New York Reports 3d": "N.Y.3d", 
            "West\u2019s New York Supplement": "N.Y.S.", 
            "West\u2019s New York Supplement 2d": "N.Y.S.2d", 
            "West\u2019s New York Supplement 3d": "N.Y.S.3d"
        }, 
        "hereinafter": {}, 
        "institution-entire": {}, 
        "institution-part": {}, 
        "nickname": {}, 
        "number": {}, 
        "place": {}, 
        "title": {}, 
        "title-phrase": {}
    }, 
    "us;oh": {
        "classic": {}, 
        "collection-title": {}, 
        "container-phrase": {}, 
        "container-title": {
            "Ohio Reports": "Ohio", 
            "Ohio St.3d": "Ohio St. 3d", 
            "Ohio State Reports 3d": "Ohio St. 3d"
        }, 
        "hereinafter": {}, 
        "institution-entire": {
            "Ohio": "Ohio"
        }, 
        "institution-part": {}, 
        "nickname": {}, 
        "number": {}, 
        "place": {}, 
        "title": {}, 
        "title-phrase": {}
    }, 
    "us;ok": {
        "classic": {}, 
        "collection-title": {}, 
        "container-phrase": {}, 
        "container-title": {
            "Oklahoma Reports": "Okla."
        }, 
        "hereinafter": {}, 
        "institution-entire": {}, 
        "institution-part": {}, 
        "nickname": {}, 
        "number": {}, 
        "place": {}, 
        "title": {}, 
        "title-phrase": {}
    }, 
    "us;or": {
        "classic": {}, 
        "collection-title": {}, 
        "container-phrase": {}, 
        "container-title": {
            "Oregon Reports": "Or."
        }, 
        "hereinafter": {}, 
        "institution-entire": {}, 
        "institution-part": {}, 
        "nickname": {}, 
        "number": {}, 
        "place": {}, 
        "title": {}, 
        "title-phrase": {}
    }, 
    "us;pa": {
        "classic": {}, 
        "collection-title": {}, 
        "container-phrase": {}, 
        "container-title": {
            "Pa. Commonwealth Ct.": "Pa. Commw.", 
            "Pa. Superior Ct.": "Pa. Super.", 
            "Pennsylvania Commonwealth Court Reports": "Pa. Commw.", 
            "Pennsylvania State Reports": "Pa.", 
            "Pennsylvania Superior Court Reports": "Pa. Super."
        }, 
        "hereinafter": {}, 
        "institution-entire": {}, 
        "institution-part": {}, 
        "nickname": {}, 
        "number": {}, 
        "place": {}, 
        "title": {}, 
        "title-phrase": {}
    }, 
    "us;pr": {
        "classic": {}, 
        "collection-title": {}, 
        "container-phrase": {}, 
        "container-title": {
            "Puerto Rico": "P.R.", 
            "Puerto Rico Reports": "P.R."
        }, 
        "hereinafter": {}, 
        "institution-entire": {}, 
        "institution-part": {}, 
        "nickname": {}, 
        "number": {}, 
        "place": {}, 
        "title": {}, 
        "title-phrase": {}
    }, 
    "us;ri": {
        "classic": {}, 
        "collection-title": {}, 
        "container-phrase": {}, 
        "container-title": {
            "Rhode Island Reports": "R.I."
        }, 
        "hereinafter": {}, 
        "institution-entire": {}, 
        "institution-part": {}, 
        "nickname": {}, 
        "number": {}, 
        "place": {}, 
        "title": {}, 
        "title-phrase": {}
    }, 
    "us;sc": {
        "classic": {}, 
        "collection-title": {}, 
        "container-phrase": {}, 
        "container-title": {
            "South Carolina Reports": "S.C."
        }, 
        "hereinafter": {}, 
        "institution-entire": {}, 
        "institution-part": {}, 
        "nickname": {}, 
        "number": {}, 
        "place": {}, 
        "title": {}, 
        "title-phrase": {}
    }, 
    "us;sd": {
        "classic": {}, 
        "collection-title": {}, 
        "container-phrase": {}, 
        "container-title": {
            "South Dakota Reports": "S.D."
        }, 
        "hereinafter": {}, 
        "institution-entire": {}, 
        "institution-part": {}, 
        "nickname": {}, 
        "number": {}, 
        "place": {}, 
        "title": {}, 
        "title-phrase": {}
    }, 
    "us;tn": {
        "classic": {}, 
        "collection-title": {}, 
        "container-phrase": {}, 
        "container-title": {
            "Tennessee Reports": "Tenn."
        }, 
        "hereinafter": {}, 
        "institution-entire": {}, 
        "institution-part": {}, 
        "nickname": {}, 
        "number": {}, 
        "place": {}, 
        "title": {}, 
        "title-phrase": {}
    }, 
    "us;tx": {
        "classic": {}, 
        "collection-title": {}, 
        "container-phrase": {}, 
        "container-title": {
            "Texas Reports": "Tex."
        }, 
        "hereinafter": {}, 
        "institution-entire": {}, 
        "institution-part": {}, 
        "nickname": {}, 
        "number": {}, 
        "place": {}, 
        "title": {}, 
        "title-phrase": {}
    }, 
    "us;ut": {
        "classic": {}, 
        "collection-title": {}, 
        "container-phrase": {}, 
        "container-title": {
            "Utah Reports": "Utah"
        }, 
        "hereinafter": {}, 
        "institution-entire": {}, 
        "institution-part": {}, 
        "nickname": {}, 
        "number": {}, 
        "place": {}, 
        "title": {}, 
        "title-phrase": {}
    }, 
    "us;va": {
        "classic": {}, 
        "collection-title": {}, 
        "container-phrase": {}, 
        "container-title": {
            "Virginia Court of Appeals Reports": "Va. App.", 
            "Virginia Reports": "Va."
        }, 
        "hereinafter": {}, 
        "institution-entire": {}, 
        "institution-part": {}, 
        "nickname": {}, 
        "number": {}, 
        "place": {}, 
        "title": {}, 
        "title-phrase": {}
    }, 
    "us;vt": {
        "classic": {}, 
        "collection-title": {}, 
        "container-phrase": {}, 
        "container-title": {
            "Vermont Reports": "Vt."
        }, 
        "hereinafter": {}, 
        "institution-entire": {}, 
        "institution-part": {}, 
        "nickname": {}, 
        "number": {}, 
        "place": {}, 
        "title": {}, 
        "title-phrase": {}
    }, 
    "us;wa": {
        "classic": {}, 
        "collection-title": {}, 
        "container-phrase": {}, 
        "container-title": {
            "Washington Appellate Reports": "Wash. App.", 
            "Washington Reports": "Wash.", 
            "Washington Reports 2d": "Wash. 2d", 
            "Washington Territory Reports": "Wash. Terr.", 
            "Wn": "Wash.", 
            "Wn. 2d": "Wash. 2d", 
            "Wn. App.": "Wash. App.", 
            "Wn. Terr.": "Wash. Terr.", 
            "Wn.2d": "Wash. 2d", 
            "Wn.App.": "Wash. App."
        }, 
        "hereinafter": {}, 
        "institution-entire": {}, 
        "institution-part": {}, 
        "nickname": {}, 
        "number": {}, 
        "place": {}, 
        "title": {}, 
        "title-phrase": {}
    }, 
    "us;wi": {
        "classic": {}, 
        "collection-title": {}, 
        "container-phrase": {}, 
        "container-title": {
            "Wis.2d": "Wis. 2d", 
            "Wisconsin Reports": "Wis.", 
            "Wisconsin Reports 2d": "Wis. 2d"
        }, 
        "hereinafter": {}, 
        "institution-entire": {
            "Court of Appeals": "WI App", 
            "Supreme Court": "WI"
        }, 
        "institution-part": {}, 
        "nickname": {}, 
        "number": {}, 
        "place": {}, 
        "title": {}, 
        "title-phrase": {}
    }, 
    "us;wv": {
        "classic": {}, 
        "collection-title": {}, 
        "container-phrase": {}, 
        "container-title": {
            "West Virginia Reports": "W.Va."
        }, 
        "hereinafter": {}, 
        "institution-entire": {}, 
        "institution-part": {}, 
        "nickname": {}, 
        "number": {}, 
        "place": {}, 
        "title": {}, 
        "title-phrase": {}
    }, 
    "us;wy": {
        "classic": {}, 
        "collection-title": {}, 
        "container-phrase": {}, 
        "container-title": {
            "Wyoming Reports": "Wyo."
        }, 
        "hereinafter": {}, 
        "institution-entire": {}, 
        "institution-part": {}, 
        "nickname": {}, 
        "number": {}, 
        "place": {}, 
        "title": {}, 
        "title-phrase": {}
    }
}